MANIFEST.in
setup.py
achievements/__init__.py
achievements/admin.py
achievements/engine.py
achievements/models.py
achievements/signals.py
achievements/tasks.py
achievements/utils.py
achievements/migrations/0001_initial.py
achievements/migrations/0002_auto__del_field_userachievement_profile__add_field_userachievement_use.py
achievements/migrations/__init__.py
achievements/templatetags/__init__.py
django_achievements.egg-info/PKG-INFO
django_achievements.egg-info/SOURCES.txt
django_achievements.egg-info/dependency_links.txt
django_achievements.egg-info/requires.txt
django_achievements.egg-info/top_level.txt